keras_cortex/__init__.py
keras_cortex/activations.py
keras_cortex/layers.py
keras_cortex/cornet/__init__.py
keras_cortex/cornet/cornet_s.py
keras_cortex/cornet/cornet_z.py
keras_cortex/cornet/util.py
keras_cortex-0.0.8.dist-info/LICENSE
keras_cortex-0.0.8.dist-info/METADATA
keras_cortex-0.0.8.dist-info/WHEEL
keras_cortex-0.0.8.dist-info/top_level.txt
keras_cortex-0.0.8.dist-info/RECORD
