Metadata-Version: 2.1
Name: keras-cortex
Version: 0.0.8
Summary: Keras Implementations of Goal-driven models of (parts of) cortex
Home-page: https://github.com/weidler/keras-cortex
Author: Tonio Weidler
Author-email: research@tonioweidler.de
License: Apache-2.0
Classifier: Development Status :: 2 - Pre-Alpha
Classifier: Intended Audience :: Science/Research
Classifier: License :: OSI Approved :: GNU General Public License v3 (GPLv3)
Classifier: Operating System :: POSIX :: Linux
Classifier: Programming Language :: Python :: 3
Classifier: Programming Language :: Python :: 3.5
Classifier: Programming Language :: Python :: 3.6
Classifier: Programming Language :: Python :: 3.7
Classifier: Programming Language :: Python :: 3.8
License-File: LICENSE
Requires-Dist: tensorflow
